[1,["ecpdLyjvZBwrvm+cedCcQy","a7MlS2gqBNBZdyvtQNAPxv","a2MjXRFdtLlYQ5ouAFv/+R","4eV2gxL7lD5aY4wvX8DaDy","ffRJ5IeVRAt7CgT6szZGX/","0cPcZIZuZI1ZazoYrP4Rx1","6fmurUmTRAM5OuEL8cJxZh","9by/L2R7tLf7HTvt7O6nZH","1c2o8K8/lCrrxb/mB5RiAs","1ehPgV6l5K/5h6grLWAnmG","43vanKhjJFEbZFKosc0X9i","78B8AF5x5LXqTehXeji0vy","4anZGkL8lPJrjgxe5XO6NT","50MEwo4ftAwKrnwIKBqad+"],["node","_spriteFrame","_textureSetter","root","_parent","numberSpriteAtlas","numberBlurSpriteAtlas","_defaultClip","vfxINode","bonusNumberDisplay","coinDisplayHolder","gameRoundNumberDisplay","playedGameRoundHolder","bonusAnim","bonusHolder","backButton","nextGameButton","homeButton","buttonHolder","loseAnim","gamesTextSprite","bonusTextSprite","descTextSprite","nextTimeTextSprite","oopsTextSprite","data","coinDisplayPrefab","buttonPrefab"],[["cc.Node",["_name","_prefab","_parent","_trs","_contentSize","_children","_components"],2,4,1,7,5,2,12],"cc.SpriteFrame",["cc.Node",["_name","_parent","_components","_prefab","_trs","_contentSize","_children","_anchorPoint"],2,1,2,4,7,5,2,5],["cc.Node",["_name","_opacity","_parent","_components","_prefab","_contentSize","_trs","_children","_color","_anchorPoint"],1,1,9,4,5,7,2,5,5],["cc.Sprite",["_sizeMode","_isTrimmedMode","_materials","node","_spriteFrame"],1,3,1,6],["cc.PrefabInfo",["fileId","root","asset"],2,1,1],["cc.Layout",["_resize","_N$layoutType","_N$affectedByScale","_N$spacingX","_N$horizontalDirection","node","_layoutSize"],-2,1,5],["e13cc9FLShL66GevrFVSv5p",["kSprite","nodeNumberWidth","decimalNumberY","spriteColor","enableDecimal","maxContainerSize","commaWidth","commaY","decimalWidth","decimalY","decimalNumberWidth","decimalNumberScale","node","numberContainer"],-9,1,1],["cc.AnimationClip",["_name","_duration","sample","curveData"],0,11],["cc.Prefab",["_name"],2],["cc.Node",["_name","_parent","_children","_prefab","_trs"],2,1,12,4,7],["79c647ju5JDc5USdzVBxgpQ",["node","oopsTextSprite","nextTimeTextSprite","descTextSprite","bonusTextSprite","gamesTextSprite","loseAnim","buttonHolder","homeButton","nextGameButton","backButton","bonusHolder","bonusAnim","playedGameRoundHolder","gameRoundNumberDisplay","coinDisplayHolder","bonusNumberDisplay","nodesToHide","vfxINode","coinDisplayPrefab","buttonPrefab"],3,1,1,1,1,1,1,1,1,1,1,1,1,1,1,1,1,1,2,1,6,6],["cc.Animation",["node","_clips"],3,1,3],["cc.Button",["zoomScale","node","clickEvents","_N$target"],2,1,9,1],["cc.ClickEvent",["_componentId","handler","customEventData","target"],0,1]],[[5,0,1,2,2],[4,0,1,3,2,4,3],[4,0,1,3,2,3],[3,0,2,3,4,5,6,2],[0,0,6,1,4,3,2],[5,0,1,2],[13,0,1,2,3,2],[14,0,1,2,3,4],[8,0,1,2,3,4],[0,0,2,1,3,2],[0,0,2,5,1,4,3,2],[2,0,1,2,3,5,4,2],[2,0,1,2,3,5,7,4,2],[3,0,2,7,3,4,5,6,2],[3,0,1,2,3,4,8,5,3],[12,0,1,1],[9,0,2],[0,0,5,6,1,2],[0,0,2,6,1,4,3,2],[0,0,2,5,1,4,2],[2,0,1,6,2,3,2],[2,0,1,2,3,4,2],[3,0,2,7,3,4,5,9,6,2],[10,0,1,2,3,4,2],[11,0,1,2,3,4,5,6,7,8,9,10,11,12,13,14,15,16,17,18,19,20,1],[5,1,2,1],[4,0,3,2,4,2],[4,0,1,2,3],[6,0,1,3,2,5,6,5],[6,0,1,2,5,6,4],[6,0,1,4,5,6,4],[7,4,0,1,2,3,12,13,6],[7,5,0,1,6,7,8,9,10,2,11,3,12,13,12]],[[[{"name":"lose_vfx_b_normal","rect":[313,557,534,511],"offset":[0,0],"originalSize":[534,511],"capInsets":[0,0,0,0]}],[1],0,[0],[2],[1]],[[{"name":"lose_vfx_e_normal","rect":[313,1070,588,379],"offset":[0,0],"originalSize":[588,379],"capInsets":[0,0,0,0]}],[1],0,[0],[2],[1]],[[{"name":"lose_vfx_h_normal","rect":[1,1,1459,310],"offset":[0,0],"originalSize":[1459,310],"rotated":1,"capInsets":[0,0,0,0]}],[1],0,[0],[2],[1]],[[[8,"collect_coin",0.5,20,[{},"paths",11,[{"tint_node":{"comps":{},"props":{"opacity":[{"frame":0,"value":0},{"frame":0.15,"value":150}]}}},"bonus_amount_holder",11,[{"comps":{}},"props",11,[{"opacity":[{"frame":0,"value":255}]},"scale",12,[[[{"frame":0,"curve":"linear"},"value",8,[0,0.5,0.5]],[{"frame":0.15},"value",8,[0,1.2,1.2]],[{"frame":0.3},"value",8,[0,0.97,0.97]],[{"frame":0.4},"value",8,[0,1,1]]],11,11,11,11]]],"lose_vfx_i_normal",11,[{"comps":{}},"props",11,[{"opacity":[{"frame":0,"value":255}]},"scale",12,[[[{"frame":0},"value",8,[0,1.3,1.3]],[{"frame":0.15},"value",8,[0,1.43,1.43]],[{"frame":0.5},"value",8,[0,1.45,1.45]]],11,11,11]]],"lose_vfx_h_normal",11,[{"comps":{}},"props",11,[{"opacity":[{"frame":0,"value":255}]},"scale",12,[[[{"frame":0,"curve":"quadOut"},"value",8,[0,1.33,1.33]],[{"frame":0.25},"value",8,[0,1.43,1.43]]],11,11]]],"text_bonus",11,[{"comps":{}},"props",11,[{"position":[{"frame":0,"curve":"expoOut","value":[0,80,0]},{"frame":0.2,"curve":"linear","value":[0,275,0]},{"frame":0.35,"value":[0,250,0]},{"frame":0.45,"value":[0,265,0]},{"frame":0.5,"value":[0,262,0]}],"opacity":[{"frame":0,"value":255}]},"scale",12,[[[{"frame":0,"curve":"quadOut"},"value",8,[0,1.3,1.3]],[{"frame":0.15},"value",8,[0,1,1]]],11,11]]]]]]],0,0,[],[],[]],[[{"name":"lose_vfx_i_normal","rect":[313,1451,641,269],"offset":[0,0],"originalSize":[641,269],"capInsets":[0,0,0,0]}],[1],0,[0],[2],[1]],[[{"name":"lose_vfx_a_normal","rect":[313,1,641,554],"offset":[0,0],"originalSize":[641,554],"capInsets":[0,0,0,0]}],[1],0,[0],[2],[1]],[[[16,"lose_controller"],[17,"lose_controller",[-29,-30,-31,-32,-33,-34],[[[24,-27,-26,-25,-24,-23,-22,-21,-20,-19,-18,-17,-16,-15,-14,-13,-12,-11,[-3,-4,-5,-6,-7,-8,-9,-10],-2,23,24],-28],4,1],[25,-1,0]],[20,"bonus_ui",1,[-36,-37,-38,-39,-40,-41],[-35],[0,"91WCU11wxG8ZgVUqh4yLYp",1,0]],[13,"lose_vfx_b",1,[-43,-44,-45],[[1,2,false,-42,[7],8]],[0,"eb9xxxZC1P8bW2frtGdWAP",1,0],[5,534,511],[0,0,0,0,0,0,1,1,1,1.43]],[23,"button_holder",1,[[-46,-47,-48,[9,"bet_amount_display_holder",-49,[0,"fbQ64In3tDYb6PDfHUIfRi",1,0],[250,-800,0,0,0,0,1,1,1,1]]],1,1,1,4],[0,"96mwe9ofVN0oS3/yJzrFsz",1,0],[0,-510,0,0,0,0,1,1,1,1]],[13,"game_round_holder",3,[-51,-52],[[28,1,1,20,true,-50,[5,46,50.4]]],[0,"e2j531UJpH6aE1LNmPXOP7",1,0],[5,46,50.4],[0,0,0,0,0,0,1,1,1,1.43]],[14,"tint_node",0,2,[[26,0,-54,[11],12]],[5,"a88JyruLdFdqxKiLNDlGxl",-53],[4,4278190080],[5,1080,2340]],[3,"lose_vfx_i_normal",2,[[1,2,false,-55,[15],16]],[0,"11C4lIHuBBvITVKszXlEvF",1,0],[5,641,269],[0,-40,0,0,0,0,1,1,1,1]],[22,"bonus_amount_holder",2,[-57],[[29,1,1,true,-56,[5,0,200]]],[0,"e8I8aWI6JFnbOQBnoqne7h",1,0],[5,0,200],[0,0.5,1],[0,50,0,0,0,0,1,1,1,1]],[18,"number_display",8,[[-58,[30,1,1,1,-59,[5,0,200]]],1,4],[0,"e6H65uDoVASbFGnesbQCVD",1,0],[5,0,200],[0,-125,0,0,0,0,1,1,1,1]],[4,"home_button",[[[2,2,false,-60,[19]],-61],4,1],[0,"6d+Ogky5FPTJFlunPVE1k6",1,0],[5,477,182],[0,0,0,0,0,0,1,0.8,0.8,0]],[4,"next_game_button",[[[2,2,false,-62,[20]],-63],4,1],[0,"71T0fe62JCaqkduXt6NlvI",1,0],[5,477,181],[0,0,0,0,0,0,1,0.8,0.8,0]],[4,"back_button",[[[2,2,false,-64,[21]],-65],4,1],[0,"29YbhyHw5PT6gMiWYwjfws",1,0],[5,477,182],[0,0,0,0,0,0,1,0.8,0.8,0]],[14,"tint_node",150,1,[[1,0,false,-67,[0],1]],[5,"d33paK9XZOd4gnqeuX3adf",-66],[4,4278190080],[5,1080,2340]],[3,"lose_vfx_a",1,[[1,2,false,-68,[2],3]],[0,"5fga+oa1dAI687LkaW8/u5",1,0],[5,641,554],[0,35,0,0,0,0,1,1,1,1]],[11,"game_round_number_display",5,[-69],[0,"907mCuJJpBbKIKYDZaGRVD",1,0],[5,26,38],[-10,0,0,0,0,0,1,1,1,1]],[21,"text_games",5,[-71],[5,"9ajyE4YU5P+5LYS+lMT9rI",-70],[23,0,0,0,0,0,1,1,1,1]],[27,2,false,[6]],[3,"lose_feather",1,[[1,2,false,-72,[9],10]],[0,"14z+vzvbxBFIhDLg7Jff2e",1,0],[5,588,379],[25,245,0,0,0,0,1,0.9,0.9,1]],[3,"lose_vfx_h_normal",2,[[1,2,false,-73,[13],14]],[0,"dcg5m6UHVFW4yaJDqUWcrU",1,0],[5,1459,310],[0,-40,0,0,0,0,1,1.1,1.1,1.1]],[12,"text_bonus",2,[-74],[0,"69FNYpdgRMm5c7c2SlkBel",1,0],[5,342,153],[0,0.5,1],[0,200,0,0,0,0,1,1,1,1]],[11,"text_oops",3,[-75],[0,"6fOeLvIoxOYq/CCOp1Zglw",1,0],[5,618,266],[0,135,0,0,0,0,1,0.8,0.8,0.5]],[2,2,false,21,[4]],[31,false,null,25,0,"#FFEB00",15,15],[2,2,false,16,[5]],[12,"text_nexttime",3,[17],[0,"93uOsvPB5JC6qE+hUY9tqM",1,0],[5,452,168],[0,0.5,1],[0,-30,0,0,0,0,1,0.8,0.8,1.43]],[9,"coin_display_holder",2,[0,"2c138oGs1Bn63v1yEl2pTL",1,0],[0,0,0,0,0,0,1,1,1,1.1]],[2,2,false,20,[17]],[32,800,null,150,70,-50,70,-50,150,0,1,"#FFFFFF",9,9],[15,2,[18]],[10,"home_button_holder",4,[10],[0,"6aeKw/db9B0ZsuR4RDAkpt",1,0],[5,381.6,145.6],[-250,0,0,0,0,0,1,1,1,1]],[6,0.9,10,[[7,"79c647ju5JDc5USdzVBxgpQ","buttonClick","0",1]],10],[10,"next_game_button_holder",4,[11],[0,"5642GBeGlBTbIzDSsK4ufl",1,0],[5,381.6,145.6],[250,0,0,0,0,0,1,1,1,1]],[6,0.9,11,[[7,"79c647ju5JDc5USdzVBxgpQ","buttonClick","1",1]],11],[19,"back_button_holder",4,[12],[0,"87OlrUtORPGoiN91TvVQez",1,0],[5,381.6,145.6]],[6,0.9,12,[[7,"79c647ju5JDc5USdzVBxgpQ","buttonClick","2",1]],12],[15,1,[22]]],0,[0,3,1,0,8,7,0,-1,6,0,-2,8,0,-3,18,0,-4,3,0,-5,14,0,-6,19,0,-7,7,0,-8,20,0,9,28,0,10,26,0,11,23,0,12,5,0,13,29,0,14,2,0,15,35,0,16,33,0,17,31,0,18,4,0,19,36,0,20,24,0,21,27,0,22,17,0,23,17,0,24,22,0,0,1,0,-2,36,0,-1,13,0,-2,14,0,-3,3,0,-4,18,0,-5,2,0,-6,4,0,-1,29,0,-1,6,0,-2,19,0,-3,26,0,-4,7,0,-5,20,0,-6,8,0,0,3,0,-1,21,0,-2,5,0,-3,25,0,-1,30,0,-2,32,0,-3,34,0,4,4,0,0,5,0,-1,15,0,-2,16,0,3,6,0,0,6,0,0,7,0,0,8,0,-1,9,0,-1,28,0,0,9,0,0,10,0,-2,31,0,0,11,0,-2,33,0,0,12,0,-2,35,0,3,13,0,0,13,0,0,14,0,-1,23,0,3,16,0,-1,24,0,0,18,0,0,19,0,-1,27,0,-1,22,0,25,1,10,4,30,11,4,32,12,4,34,17,0,25,75],[0,0,0,0,0,0,0,0,0,0,0,0,0,0,0,0,0,0,0,0,0,0,0,0,0,23,23,28,28,29,36],[-1,1,-1,1,-1,-1,-1,-1,1,-1,1,-1,1,-1,1,-1,1,-1,-1,-1,-1,-1,-1,26,27,5,6,5,6,7,7],[0,2,0,7,0,0,0,0,8,0,9,0,2,0,10,0,11,0,3,0,0,0,4,12,13,5,5,6,6,3,4]],[[[8,"lose",8.333333333333334,24,[{},"paths",11,[{"tint_node":{"props":{"opacity":[{"frame":0,"value":0},{"frame":0.125,"value":150}]}}},"lose_feather",11,[{},"props",11,[{"opacity":[{"frame":0,"value":0},{"frame":0.041666666666666664,"value":0},{"frame":0.125,"value":255}]},"scale",12,[[[{"frame":0.041666666666666664},"value",8,[0,1.28,1.28]],[{"frame":0.2916666666666667},"value",8,[0,1.8,1.8]],[{"frame":8.333333333333334},"value",8,[0,3,3]]],11,11,11]]],"text_oops",11,[{},"props",11,[{"opacity":[{"frame":0,"value":0},{"frame":0.16666666666666666,"value":255}],"angle":[{"frame":0.16666666666666666,"value":0},{"frame":8.333333333333334,"value":-10}]},"scale",12,[[[{"frame":0,"curve":"linear"},"value",8,[0,0.5,0.5]],[{"frame":0.16666666666666666},"value",8,[0,1,1]],[{"frame":0.2916666666666667},"value",8,[0,0.8,0.8]],[{"frame":0.3333333333333333},"value",8,[0,0.8,0.8]],[{"frame":8.333333333333334},"value",8,[0,1.2,1.2]]],11,11,11,11,11]]],"lose_vfx_b",11,[{},"props",11,[{"opacity":[{"frame":0,"value":0},{"frame":0.20833333333333334,"value":255}],"angle":[{"frame":0.20833333333333334,"value":0},{"frame":8.333333333333334,"value":-5}]},"scale",12,[[[{"frame":0},"value",8,[0,1.29,1.29]],[{"frame":0.2916666666666667},"value",8,[0,1.43,1.43]],[{"frame":0.375},"value",8,[0,1.43,1.43]],[{"frame":8.333333333333334},"value",8,[0,2,2]]],11,11,11,11]]],"lose_vfx_a",11,[{},"props",11,[{"opacity":[{"frame":0,"value":0},{"frame":0.125,"value":255}]},"scale",12,[[[{"frame":0},"value",8,[0,1.28,1.28]],[{"frame":8.333333333333334},"value",8,[0,2,2]]],11,11]]]]]]],0,0,[],[],[]]]]