[1,["46fP+wmTFAjY054SXztkZn","f77q1ldi1Awp+9rl181wVz","67TK03us5MU42jIMSiLnGM","ecpdLyjvZBwrvm+cedCcQy","a1pIgYRzdKg5GiwRLAH5x3","48lifiam9ND4UI82y8OVOj","bfrGuC2MBCKJ0CL9NIbyVj","a3xn4u5KNN6afwQnzM/q/8","baPY4TfglDBJx6maxl8Ae2","ffWcgKn41Ji7bUvvAzztQ3","779ep6h1ZK5b9Uug0Db7cF","fbDXNBnElHVqhKIfF3vZrT","4dNkTvWdZNu6mRdEvoR4Ot","5dOEEuVu9H95S5qHvWXUHL","3apmkv+uhPcIWMlS7CX+RJ","e6U0cn6YxNHqDoeNxhBpup","1bLzHtpj1JH6ybmiAxCHb4","61b/8pZFJJUZAs+pt5m2Ig","f6foRgtDFKiZSNAU7Tl5L6","6eARbmtoZOQ5xBp+E5Spfd","f5TYZNgxRDSYtzJvY5WAvZ","f3yp3H94hD0Zbi9SYmkHCu","f7KAZKAKNNnoRA2kuaZZ//","93Y9qVphlMio14qmpiZof4","f7O03yNnhA6Ydxc1zXUEFh","91qAHUbfxJBYPG2aI2uuTM","e01o7m/TRMT70azfhG05Bl","ecQeWxc9tFJpz8ZtppAqtn","7a/QZLET9IDreTiBfRn2PD","09bRdK7ehMx4oAsYjpZcTp","d8weZpM8dK2JDQ49+Rl4oJ","2aggcRwWJHP7WRRvgo0+/m","aaKoYw6q9FUbMNhX4D0WbX","e0yMyEDbhHnpzjyf9bKpmy","5baR/dV+tArr9ZEJaK0ESh","8a4wSvG2ZItaLBZE86d//M","478X9GqmFC7Lw3pUz0piEA","47YuDYWPhP/7VkW9qAcrC+","41IBSOpCJOyILS9H5FiPrX","b6ga1v0EBHxYE8GMNYdf7r","8cDkV2jjBB/5VVAkyISVcL","46RPjqVkRGdZw/44lJ/JUx","6br5L9sFNIkLTVoP6O5uz2","b46sxspZBIZY8jFk1tx3+K","6duiygaKtPhZs5GVk5JF3z","41jNy1vCJFzLJfexDRMmwg","3dtWZ2pNJGSqvckU5oO7Es","fddNKnK9lGW5ZDH347BTzW","89Uvsll4RJY5xQktlbOGBR","5apZ9sB7lO6K5A7oTfeLJ4","1299RkoeFNFK+J8gKfvkTh","4bigO+GW5At66xgphdDUxA","9bDZ3/CvhFG4D3O1ogU6UI","9exmiV2ClJy4eU9/pJPUjJ","2673hMaHpOgqwfH0oyjVtn","62qTAYSsJB66UbdhimwJPR","b2z9UlfyFGiakDDeYeVwN0","e8kdb6arBJF73gSaYaEr5U","3arp3TGtNLFIsGESVMC8hG","a31FmY5DFBaqz460kEXVBK","1eNBJlZJ5JWKVoUyenNWNp","7fJbGUrctH3YOVsQO0YIL4","d86MjCw31BY7uzMB8kVCxl","185ww1SqVGdKMi5dxuUgaf","8f2/qqw5NI77huRU9Mfq/U","c6J9cZr+tLH6kvoB1Hgt7u","2bKVRIwkRCjK/u3i++eqYF","d01/Z11zNNIY9Y3mRki5Dz","9aJy0PqdRBDqpufsJemKIX","5dpMsjo2ZK9plJFBNJVkBu"],["value","_textureSetter","node","_defaultClip","root","vfxEbeating","vfxDRedLine","vfxCBeatingSmoke","starExplodeAnim","vfxABackgroundGlow","wildSpine","wildSprite","backgroundSprite","data"],["cc.SpriteFrame",["cc.Sprite",["_sizeMode","_isTrimmedMode","_dstBlendFactor","_srcBlendFactor","node","_materials"],-1,1,3],["cc.Node",["_name","_parent","_components","_prefab","_contentSize","_trs"],2,1,2,4,5,7],["cc.PrefabInfo",["fileId","root","asset"],2,1,1],["cc.AnimationClip",["_name","_duration","sample","curveData"],0,11],["cc.Prefab",["_name"],2],["cc.Node",["_name","_children","_components","_prefab"],2,2,9,4],["cc.Node",["_name","_parent","_components","_prefab","_contentSize","_trs"],2,1,12,4,5,7],["b1971gcaklG0IM26hIKNzGZ",["node","backgroundSprite","wildSprite","wildSpine","vfxABackgroundGlow","starExplodeAnim","vfxCBeatingSmoke","vfxDRedLine","vfxEbeating"],3,1,1,1,1,1,1,1,1,1],["sp.Skeleton",["_preCacheMode","loop","node","_materials"],1,1,3],["cc.Animation",["node","_clips"],3,1,3]],[[3,0,1,2,2],[4,0,1,2,3,4],[7,0,1,2,3,4,5,2],[1,0,1,4,5,3],[10,0,1,1],[2,0,1,2,3,4,2],[1,2,0,1,4,5,4],[5,0,2],[6,0,1,2,3,2],[2,0,1,2,3,4,5,2],[8,0,1,2,3,4,5,6,7,8,1],[3,1,2,1],[1,3,2,0,1,4,5,5],[9,0,1,2,3,3]],[[[{"name":"wolf_vfx_e_normal_06","rect":[317,1,185,153],"offset":[17,16],"originalSize":[315,315],"rotated":1,"capInsets":[0,0,0,0]}],[0],0,[0],[1],[2]],[[{"name":"wolf_vfx_d_add_07","rect":[1,1,227,159],"offset":[4,26],"originalSize":[315,315],"capInsets":[0,0,0,0]}],[0],0,[0],[1],[1]],[[{"name":"wolf_vfx_c_normal_07","rect":[945,1,217,257],"offset":[3,1],"originalSize":[315,315],"capInsets":[0,0,0,0]}],[0],0,[0],[1],[0]],[[{"name":"wolf_vfx_d_add_04","rect":[1,412,181,209],"offset":[26,-3],"originalSize":[315,315],"rotated":1,"capInsets":[0,0,0,0]}],[0],0,[0],[1],[1]],[[{"name":"wolf_vfx_a_add_01","rect":[824,203,170,180],"offset":[0,0],"originalSize":[170,180],"capInsets":[0,0,0,0]}],[0],0,[0],[1],[8]],[[{"name":"wolf_vfx_e_normal_10","rect":[92,395,71,89],"offset":[-6,-1],"originalSize":[315,315],"capInsets":[0,0,0,0]}],[0],0,[0],[1],[2]],[[{"name":"wolf_vfx_d_add_10","rect":[1,329,213,81],"offset":[8,-18],"originalSize":[315,315],"capInsets":[0,0,0,0]}],[0],0,[0],[1],[1]],[[{"name":"wolf_vfx_c_normal_05","rect":[1164,1,203,257],"offset":[-4,1],"originalSize":[315,315],"capInsets":[0,0,0,0]}],[0],0,[0],[1],[0]],[[{"name":"wolf_vfx_d_add_02","rect":[216,371,139,211],"offset":[47,3],"originalSize":[315,315],"rotated":1,"capInsets":[0,0,0,0]}],[0],0,[0],[1],[1]],[[{"name":"wolf_vfx_e_normal_02","rect":[218,1,215,97],"offset":[16,58],"originalSize":[315,315],"rotated":1,"capInsets":[0,0,0,0]}],[0],0,[0],[1],[2]],[[{"name":"wolf_vfx_e_normal_01","rect":[176,385,107,71],"offset":[75,55],"originalSize":[315,315],"capInsets":[0,0,0,0]}],[0],0,[0],[1],[2]],[[[1,"beating_smoke",1.1111111111111112,18,[{},"comps",11,[{},"cc.Sprite",11,[{},"spriteFrame",12,[[[{"frame":0},"value",6,0],[{"frame":0.05555555555555555},"value",6,1],[{"frame":0.1111111111111111},"value",6,2],[{"frame":0.16666666666666666},"value",6,3],[{"frame":0.2222222222222222},"value",6,4],[{"frame":0.2777777777777778},"value",6,5],[{"frame":0.3333333333333333},"value",6,6],[{"frame":0.3888888888888889},"value",6,7],[{"frame":0.4444444444444444},"value",6,8],[{"frame":0.5},"value",6,9],[{"frame":0.5555555555555556},"value",6,10],[{"frame":0.6111111111111112},"value",6,11],[{"frame":0.6666666666666666},"value",6,12],[{"frame":0.7222222222222222},"value",6,13],[{"frame":0.7777777777777778},"value",6,14],[{"frame":0.8333333333333334},"value",6,15],[{"frame":0.8888888888888888},"value",6,16],[{"frame":0.9444444444444444},"value",6,17],[{"frame":1},"value",6,18],{"frame":1.0555555555555556,"value":null}],11,11,11,11,11,11,11,11,11,11,11,11,11,11,11,11,11,11,11,0]]]]]],0,0,[0,0,0,0,0,0,0,0,0,0,0,0,0,0,0,0,0,0,0],[0,0,0,0,0,0,0,0,0,0,0,0,0,0,0,0,0,0,0],[9,10,11,12,13,14,15,16,17,18,19,20,21,22,23,24,25,26,27]],[[{"name":"wolf_vfx_e_normal_07","rect":[373,188,95,145],"offset":[-23,15],"originalSize":[315,315],"capInsets":[0,0,0,0]}],[0],0,[0],[1],[2]],[[{"name":"wolf_vfx_c_normal_03","rect":[1447,260,193,257],"offset":[-9,1],"originalSize":[315,315],"rotated":1,"capInsets":[0,0,0,0]}],[0],0,[0],[1],[0]],[[[7,"wild_item_prefab"],[8,"wild_item_prefab",[-11,-12,-13,-14,-15,-16,-17,-18],[[10,-10,-9,-8,-7,-6,-5,-4,-3,-2]],[11,-1,0]],[2,"star_screen_00_explode",1,[[[12,1,769,2,false,-19,[4]],-20],4,1],[0,"e51/Fina1LoJxLFWX72SSA",1,0],[5,225,225],[0,0,0,0,0,0,1,1.43,1.43,1]],[2,"wolf_vfx_c_normal_00_beating_smoke",1,[[[3,2,false,-21,[6]],-22],4,1],[0,"7dRbzER8tFNZuKPB/woDk9",1,0],[5,315,315],[0,0,0,0,0,0,1,1.43,1.43,1]],[2,"wolf_vfx_d_add_00_red_line",1,[[[6,1,2,false,-23,[8]],-24],4,1],[0,"dahPT4LTlEaYrqpB+/lQ+G",1,0],[5,315,315],[0,0,0,0,0,0,1,1.43,1.43,1]],[2,"wolf_vfx_e_normal_00_beating",1,[[[3,2,false,-25,[10]],-26],4,1],[0,"56ArboyzdAF4ddeC6kcdn0",1,0],[5,315,315],[0,0,0,0,0,0,1,1.43,1.43,1]],[5,"symbol_background",1,[-27],[0,"feMpkb15hBArpSHOOatZVp",1,0],[5,350,350]],[3,2,false,6,[0]],[9,"wolf_vfx_a_add_background_glow",1,[-28],[0,"29ZzZvyB1Fb5o6HeDRb3JH",1,0],[5,170,180],[0,0,0,0,0,0,1,2,2,1]],[6,1,2,false,8,[1]],[5,"symbol",1,[-29],[0,"29NIjaZ7xFM4baIjwVdDJk",1,0],[5,350,350]],[3,2,false,10,[2]],[5,"spine",1,[-30],[0,"3bmuBaV4xAG6140Pa+98fi",1,0],[5,201.5,362]],[13,0,false,12,[3]],[4,2,[5]],[4,3,[7]],[4,4,[9]],[4,5,[11]]],0,[0,4,1,0,5,17,0,6,16,0,7,15,0,8,14,0,9,9,0,10,13,0,11,11,0,12,7,0,2,1,0,-1,6,0,-2,8,0,-3,10,0,-4,12,0,-5,2,0,-6,3,0,-7,4,0,-8,5,0,2,2,0,-2,14,0,2,3,0,-2,15,0,2,4,0,-2,16,0,2,5,0,-2,17,0,-1,7,0,-1,9,0,-1,11,0,-1,13,0,13,1,30],[0,0,0,0,0,0,0,0,0,0,0,0,14,15,16,17],[-1,-1,-1,-1,-1,-1,-1,-1,-1,-1,-1,-1,3,3,3,3],[3,3,3,28,3,4,3,5,3,6,3,7,4,5,6,7]],[[{"name":"wolf_vfx_e_normal_05","rect":[176,218,195,165],"offset":[14,12],"originalSize":[315,315],"capInsets":[0,0,0,0]}],[0],0,[0],[1],[2]],[[{"name":"wolf_vfx_c_normal_04","rect":[1369,1,201,257],"offset":[-5,1],"originalSize":[315,315],"capInsets":[0,0,0,0]}],[0],0,[0],[1],[0]],[[{"name":"wolf_vfx_d_add_13","rect":[451,1,41,41],"offset":[-71,35],"originalSize":[315,315],"capInsets":[0,0,0,0]}],[0],0,[0],[1],[1]],[[{"name":"wolf_vfx_c_normal_08","rect":[499,1,225,257],"offset":[5,1],"originalSize":[315,315],"capInsets":[0,0,0,0]}],[0],0,[0],[1],[0]],[[{"name":"wolf_vfx_e_normal_11","rect":[176,188,3,3],"offset":[-156,156],"originalSize":[315,315],"capInsets":[0,0,0,0]}],[0],0,[0],[1],[2]],[[{"name":"wolf_vfx_e_normal_00","rect":[285,385,105,63],"offset":[80,56],"originalSize":[315,315],"rotated":1,"capInsets":[0,0,0,0]}],[0],0,[0],[1],[2]],[[{"name":"wolf_vfx_c_normal_10","rect":[1,260,241,257],"offset":[8,1],"originalSize":[315,315],"rotated":1,"capInsets":[0,0,0,0]}],[0],0,[0],[1],[0]],[[{"name":"wolf_vfx_c_normal_01","rect":[1572,1,135,127],"offset":[-5,-2],"originalSize":[315,315],"rotated":1,"capInsets":[0,0,0,0]}],[0],0,[0],[1],[0]],[[{"name":"wolf_vfx_d_add_05","rect":[1,162,165,219],"offset":[5,2],"originalSize":[315,315],"rotated":1,"capInsets":[0,0,0,0]}],[0],0,[0],[1],[1]],[[{"name":"wolf_vfx_e_normal_04","rect":[1,188,205,173],"offset":[13,14],"originalSize":[315,315],"rotated":1,"capInsets":[0,0,0,0]}],[0],0,[0],[1],[2]],[[{"name":"wolf_vfx_d_add_08","rect":[212,512,195,109],"offset":[27,-16],"originalSize":[315,315],"rotated":1,"capInsets":[0,0,0,0]}],[0],0,[0],[1],[1]],[[{"name":"wolf_vfx_c_normal_16","rect":[748,260,235,219],"offset":[2,1],"originalSize":[315,315],"rotated":1,"capInsets":[0,0,0,0]}],[0],0,[0],[1],[0]],[[{"name":"wolf_vfx_c_normal_14","rect":[1190,260,255,225],"offset":[10,-4],"originalSize":[315,315],"capInsets":[0,0,0,0]}],[0],0,[0],[1],[0]],[[{"name":"wolf_vfx_d_add_12","rect":[429,371,71,79],"offset":[-85,17],"originalSize":[315,315],"capInsets":[0,0,0,0]}],[0],0,[0],[1],[1]],[[{"name":"wolf_vfx_e_normal_08","rect":[373,335,81,141],"offset":[-14,15],"originalSize":[315,315],"capInsets":[0,0,0,0]}],[0],0,[0],[1],[2]],[[{"name":"wolf_vfx_e_normal_09","rect":[1,395,73,89],"offset":[-8,-4],"originalSize":[315,315],"rotated":1,"capInsets":[0,0,0,0]}],[0],0,[0],[1],[2]],[[[1,"wild_item_star_explode",0.8888888888888888,18,[{},"comps",11,[{},"cc.Sprite",11,[{},"spriteFrame",12,[[[{"frame":0},"value",6,0],[{"frame":0.05555555555555555},"value",6,1],[{"frame":0.1111111111111111},"value",6,2],[{"frame":0.16666666666666666},"value",6,3],[{"frame":0.2222222222222222},"value",6,4],[{"frame":0.2777777777777778},"value",6,5],[{"frame":0.3333333333333333},"value",6,6],[{"frame":0.3888888888888889},"value",6,7],[{"frame":0.4444444444444444},"value",6,8],[{"frame":0.5},"value",6,9],[{"frame":0.5555555555555556},"value",6,10],[{"frame":0.6111111111111112},"value",6,11],[{"frame":0.6666666666666666},"value",6,12],[{"frame":0.7222222222222222},"value",6,13],[{"frame":0.7777777777777778},"value",6,14],{"frame":0.8333333333333334,"value":null}],11,11,11,11,11,11,11,11,11,11,11,11,11,11,11,0]]]]]],0,0,[0,0,0,0,0,0,0,0,0,0,0,0,0,0,0],[0,0,0,0,0,0,0,0,0,0,0,0,0,0,0],[29,30,31,32,33,34,35,36,37,38,39,40,41,42,43]],[[[1,"beating",0.8888888888888888,18,[{},"comps",11,[{},"cc.Sprite",11,[{},"spriteFrame",12,[[{"frame":0.1111111111111111,"value":null},[{"frame":0.16666666666666666},"value",6,0],[{"frame":0.2222222222222222},"value",6,1],[{"frame":0.2777777777777778},"value",6,2],[{"frame":0.3333333333333333},"value",6,3],[{"frame":0.3888888888888889},"value",6,4],[{"frame":0.4444444444444444},"value",6,5],[{"frame":0.5},"value",6,6],[{"frame":0.5555555555555556},"value",6,7],[{"frame":0.6111111111111112},"value",6,8],[{"frame":0.6666666666666666},"value",6,9],[{"frame":0.7222222222222222},"value",6,10],[{"frame":0.7777777777777778},"value",6,11],{"frame":0.8333333333333334,"value":null}],0,11,11,11,11,11,11,11,11,11,11,11,11,0]]]]]],0,0,[0,0,0,0,0,0,0,0,0,0,0,0],[0,0,0,0,0,0,0,0,0,0,0,0],[44,45,46,47,48,49,50,51,52,53,54,55]],[[{"name":"wolf_vfx_d_add_03","rect":[222,192,177,215],"offset":[28,0],"originalSize":[315,315],"rotated":1,"capInsets":[0,0,0,0]}],[0],0,[0],[1],[1]],[[{"name":"wolf_vfx_d_add_00","rect":[439,192,63,55],"offset":[47,74],"originalSize":[315,315],"rotated":1,"capInsets":[0,0,0,0]}],[0],0,[0],[1],[1]],[[[1,"red_outline",1.1111111111111112,18,[{},"comps",11,[{},"cc.Sprite",11,[{},"spriteFrame",12,[[{"frame":0.2222222222222222,"value":null},[{"frame":0.2777777777777778},"value",6,0],[{"frame":0.3333333333333333},"value",6,1],[{"frame":0.3888888888888889},"value",6,2],[{"frame":0.4444444444444444},"value",6,3],[{"frame":0.5},"value",6,4],[{"frame":0.5555555555555556},"value",6,5],[{"frame":0.6111111111111112},"value",6,6],[{"frame":0.6666666666666666},"value",6,7],[{"frame":0.7222222222222222},"value",6,8],[{"frame":0.7777777777777778},"value",6,9],[{"frame":0.8333333333333334},"value",6,10],[{"frame":0.8888888888888888},"value",6,11],[{"frame":0.9444444444444444},"value",6,12],[{"frame":1},"value",6,13],{"frame":1.0555555555555556,"value":null}],0,11,11,11,11,11,11,11,11,11,11,11,11,11,11,0]]]]]],0,0,[0,0,0,0,0,0,0,0,0,0,0,0,0,0],[0,0,0,0,0,0,0,0,0,0,0,0,0,0],[56,57,58,59,60,61,62,63,64,65,66,67,68,69]],[[{"name":"wolf_vfx_d_add_09","rect":[1,595,155,109],"offset":[47,-29],"originalSize":[315,315],"capInsets":[0,0,0,0]}],[0],0,[0],[1],[1]],[[{"name":"wolf_vfx_d_add_11","rect":[323,615,143,103],"offset":[-49,4],"originalSize":[315,315],"capInsets":[0,0,0,0]}],[0],0,[0],[1],[1]],[[{"name":"wolf_vfx_d_add_06","rect":[230,1,189,219],"offset":[-15,2],"originalSize":[315,315],"rotated":1,"capInsets":[0,0,0,0]}],[0],0,[0],[1],[1]],[[{"name":"wolf_vfx_c_normal_17","rect":[969,260,231,219],"offset":[1,0],"originalSize":[315,315],"rotated":1,"capInsets":[0,0,0,0]}],[0],0,[0],[1],[0]],[[{"name":"wolf_vfx_c_normal_06","rect":[726,1,217,257],"offset":[3,1],"originalSize":[315,315],"capInsets":[0,0,0,0]}],[0],0,[0],[1],[0]],[[{"name":"wolf_vfx_d_add_01","rect":[323,512,101,157],"offset":[66,29],"originalSize":[315,315],"rotated":1,"capInsets":[0,0,0,0]}],[0],0,[0],[1],[1]],[[{"name":"wolf_vfx_c_normal_18","rect":[1447,455,41,29],"offset":[-79,34],"originalSize":[315,315],"rotated":1,"capInsets":[0,0,0,0]}],[0],0,[0],[1],[0]],[[{"name":"wolf_vfx_c_normal_12","rect":[1,1,249,257],"offset":[8,1],"originalSize":[315,315],"capInsets":[0,0,0,0]}],[0],0,[0],[1],[0]],[[{"name":"wolf_vfx_c_normal_11","rect":[252,1,245,257],"offset":[8,1],"originalSize":[315,315],"capInsets":[0,0,0,0]}],[0],0,[0],[1],[0]],[[{"name":"wolf_vfx_c_normal_09","rect":[489,260,235,257],"offset":[7,1],"originalSize":[315,315],"rotated":1,"capInsets":[0,0,0,0]}],[0],0,[0],[1],[0]],[[{"name":"wolf_vfx_c_normal_13","rect":[1706,1,251,253],"offset":[9,1],"originalSize":[315,315],"rotated":1,"capInsets":[0,0,0,0]}],[0],0,[0],[1],[0]],[[{"name":"wolf_vfx_c_normal_15","rect":[260,260,241,227],"offset":[18,-4],"originalSize":[315,315],"rotated":1,"capInsets":[0,0,0,0]}],[0],0,[0],[1],[0]],[[{"name":"wolf_vfx_c_normal_02","rect":[1706,254,173,253],"offset":[-5,1],"originalSize":[315,315],"rotated":1,"capInsets":[0,0,0,0]}],[0],0,[0],[1],[0]],[[{"name":"wolf_vfx_e_normal_03","rect":[1,1,215,185],"offset":[12,11],"originalSize":[315,315],"capInsets":[0,0,0,0]}],[0],0,[0],[1],[2]],[[{"name":"wolf_vfx_c_normal_00","rect":[1572,138,81,83],"offset":[-3,0],"originalSize":[315,315],"capInsets":[0,0,0,0]}],[0],0,[0],[1],[0]]]]