[1,["7fcP8YznNPeZFrPDYEmPG4"],["_textureSetter"],["cc.SpriteFrame"],0,[[[{"name":"big_0","rect":[768,1,162,203],"offset":[0,0],"originalSize":[162,203],"capInsets":[0,0,0,0]}],[0],0,[0],[0],[0]],[[{"name":"big_6","rect":[1096,1,152,203],"offset":[0,0],"originalSize":[152,203],"capInsets":[0,0,0,0]}],[0],0,[0],[0],[0]],[[{"name":"big_1","rect":[487,1,116,205],"offset":[0,0],"originalSize":[116,205],"capInsets":[0,0,0,0]}],[0],0,[0],[0],[0]],[[{"name":"big_5","rect":[331,1,154,206],"offset":[0,0],"originalSize":[154,206],"capInsets":[0,0,0,0]}],[0],0,[0],[0],[0]],[[{"name":"big_8","rect":[605,1,161,204],"offset":[0,0],"originalSize":[161,204],"capInsets":[0,0,0,0]}],[0],0,[0],[0],[0]],[[{"name":"big_9","rect":[932,1,162,203],"offset":[0,0],"originalSize":[162,203],"capInsets":[0,0,0,0]}],[0],0,[0],[0],[0]],[[{"name":"big_7","rect":[1250,1,147,202],"offset":[0,0],"originalSize":[147,202],"capInsets":[0,0,0,0]}],[0],0,[0],[0],[0]],[[{"name":"big_4","rect":[1399,1,152,201],"offset":[0,0],"originalSize":[152,201],"capInsets":[0,0,0,0]}],[0],0,[0],[0],[0]],[[{"name":"big_3","rect":[171,1,158,206],"offset":[0,0],"originalSize":[158,206],"capInsets":[0,0,0,0]}],[0],0,[0],[0],[0]],[[{"name":"big_2","rect":[1,1,168,207],"offset":[0,0],"originalSize":[168,207],"capInsets":[0,0,0,0]}],[0],0,[0],[0],[0]]]]